pyxi_process_manager/__init__.py
pyxi_process_manager/cmd_processor.py
pyxi_process_manager/cmd_processor_emulator.py
pyxi_process_manager/cmd_processor_manager.py
pyxi_process_manager/cmd_provider.py
pyxi_process_manager/cmd_provider_emulator.py
pyxi_process_manager/cmd_provider_manager.py
pyxi_process_manager/process_cmd.py
pyxi_process_manager/process_configuration.py
pyxi_process_manager/process_manager.py
pyxi_process_manager/process_metadata_service.py
pyxi_process_manager/root_process_cmd.py
pyxi_process_manager/secret_provider.py
pyxi_process_manager/thread_pool_manager.py
pyxi_process_manager-0.0.10.dist-info/LICENSE
pyxi_process_manager-0.0.10.dist-info/METADATA
pyxi_process_manager-0.0.10.dist-info/WHEEL
pyxi_process_manager-0.0.10.dist-info/top_level.txt
pyxi_process_manager-0.0.10.dist-info/RECORD
