Metadata-Version: 2.1
Name: pyxi-process-manager
Version: 0.0.10
Summary: A simple process manager in python.
Home-page: https://github.com/stiproot/py-process-manager
Author: Simon Stipcich
Author-email: stipcich.simon@gmail.com
License: MIT
Keywords: python,package,process,beta
Classifier: Intended Audience :: Developers
Classifier: License :: OSI Approved :: MIT License
Classifier: Programming Language :: Python :: 3.11
License-File: LICENSE
Requires-Dist: environs
